src/cpu_defs.vh
`ifndef CPU_DEFS_VH
`define CPU_DEFS_VH

// ===========================================================
// CPU GLOBAL CONSTANTS / OPCODES / ALU CODES / STATES
// ===========================================================

// ---------- Instruction Format ----------
`define INSTR_W   11
`define ADDR_W    4
`define DATA_W    4

// Extract fields
`define GET_OPCODE(x)   (x[10:8])
`define GET_OP1(x)      (x[7:4])
`define GET_OP2(x)      (x[3:0])

// ---------- OPCODES ----------
`define OPC_STO   3'b000
`define OPC_ADD   3'b001
`define OPC_SUB   3'b010
`define OPC_AND   3'b011
`define OPC_OR    3'b100
`define OPC_XOR   3'b101
`define OPC_NOT   3'b110
// (3'b111 reserved)

// ---------- FSM States ----------
`define ST_INIT    2'b00
`define ST_FETCH   2'b01
`define ST_EXEC    2'b10
`define ST_STORE   2'b11

// ---------- ALU Select Codes ----------
// We'll use 4-bit ALU select tokens = {alu_sel[2:0], cin}
// Use `casez` in logic so '-'/'?' positions act as don't cares.

// Arithmetic / Transfer (cin is meaningful)
`define ALU_TRANSFER     4'b0000
`define ALU_INC          4'b0001

`define ALU_ADD_AB       4'b0010
`define ALU_ADD_ABCIN    4'b0011

`define ALU_SUB_A_B      4'b0100
`define ALU_SUB_A_B_1    4'b0101

`define ALU_DEC          4'b0110
`define ALU_PASS_A       4'b0111

// Logical Ops (cin ignored -> use '?' in pattern macros with casez)
`define ALU_OR_MASK      4'b100?   // casez pattern: matches 1000 or 1001
`define ALU_XOR_MASK     4'b101?   // matches 1010 or 1011
`define ALU_AND_MASK     4'b110?   // matches 1100 or 1101
`define ALU_NOT_MASK     4'b111?   // matches 1110 or 1111

// ---------- RAM Control ----------
`define RAM_ACTIVE  1'b0
`define RAM_IDLE    1'b1
`define RAM_READ    1'b1
`define RAM_WRITE   1'b0

`endif

src/ram16x4.v
`timescale 1ns/1ps

module ram16x4(
    output reg [3:0] data_out,
    input [3:0] data_in,
    input [3:0] addr,
    input csn,
    input rwn,
    input clk, rst_n
); 

reg [3:0] mem [15:0];

integer i;
always @(posedge clk or negedge rst_n) begin
    //Asynchronous Reset of RAM Memory
    if (!rst_n) begin
        for (i=0; i<16; i=i+1) begin
            mem[i] <= 4'b0000;
        end
    data_out <= 4'b0000;
    end

    else if (!csn) begin 
        if (!rwn) begin
            // WRITE operation
            mem[addr] <= data_in;
            data_out  <= 4'b0000;   
        end

        else begin
            // READ operation
            data_out <= mem[addr];
        end
    end

end

endmodule

src/xor_gate.v
`timescale 1ns/1ps

module xor_gate (
    input  wire a,
    input  wire b,
    output wire c
);
    assign c = (a & ~b) | (~a & b);
endmodule

src/full_adder1.v
`timescale 1ns/1ps

module full_adder1 (
    output wire sum,
    output wire cout,
    input  wire a,
    input  wire b,
    input  wire cin
);
    wire s_ab;      // a ^ b
    wire c1, c2;    // carry terms

    xor_gate u_xor_ab  (.c(s_ab), .a(a),    .b(b));
    xor_gate u_xor_sum (.c(sum),  .a(s_ab), .b(cin));

    assign c1  = a & b;
    assign c2  = cin & s_ab;
    assign cout = c1 | c2;
endmodule

src/full_adder4.v
`timescale 1ns/1ps

module full_adder4 (
    output wire [3:0] sum,
    output wire       cout,
    input  wire [3:0] a,
    input  wire [3:0] b,
    input  wire       cin
);
    // Internal carry wires
    wire c1, c2, c3;

    // Ripple Carry Architecture using full_adder1
    full_adder1 fa0 (.sum(sum[0]), .cout(c1),   .a(a[0]), .b(b[0]), .cin(cin));
    full_adder1 fa1 (.sum(sum[1]), .cout(c2),   .a(a[1]), .b(b[1]), .cin(c1));
    full_adder1 fa2 (.sum(sum[2]), .cout(c3),   .a(a[2]), .b(b[2]), .cin(c2));
    full_adder1 fa3 (.sum(sum[3]), .cout(cout), .a(a[3]), .b(b[3]), .cin(c3));

endmodule

src/reg_alu4.v
`timescale 1ns/1ps
`include "cpu_defs.vh"

module reg_alu (
    output reg  [3:0] f,
    output reg        cout,
    input  wire       clk,
    input  wire       reset_n,
    input  wire       alu_en,   // Clock Enable
    input  wire [3:0] alu_sel,
    input  wire [3:0] a,
    input  wire [3:0] b
);
    // 1. Decode & Arith Setup
    wire s2=alu_sel[3], s1=alu_sel[2], s0=alu_sel[1], cin_in=alu_sel[0];
    reg [3:0] adder_b;

    always @(*) begin
        case ({s1, s0})
            2'b00: adder_b = 4'b0000;
            2'b01: adder_b = b;
            2'b10: adder_b = ~b;
            2'b11: adder_b = 4'b1111;
        endcase
    end

    // 2. Calculation Units
    wire [3:0] sum_out;
    wire       cout_arith;
    full_adder4 u_adder (.sum(sum_out), .cout(cout_arith), .a(a), .b(adder_b), .cin(cin_in));

    reg [3:0] logic_res;
    wire [3:0] xor_res;
    xor_gate u_xor0 (.c(xor_res[0]), .a(a[0]), .b(b[0]));
    xor_gate u_xor1 (.c(xor_res[1]), .a(a[1]), .b(b[1]));
    xor_gate u_xor2 (.c(xor_res[2]), .a(a[2]), .b(b[2]));
    xor_gate u_xor3 (.c(xor_res[3]), .a(a[3]), .b(b[3]));

    always @(*) begin
        casez (alu_sel)
            `ALU_OR_MASK:  logic_res = a | b;
            `ALU_AND_MASK: logic_res = a & b;
            `ALU_XOR_MASK: logic_res = xor_res;
            `ALU_NOT_MASK: logic_res = ~a;
            default:       logic_res = 4'b0000;
        endcase
    end

    // 3. Output Logic
    wire [3:0] next_f    = (s2 == 1'b0) ? sum_out : logic_res;
    wire       next_cout = (s2 == 1'b0) ? cout_arith : 1'b0;

    // 4. Sequential Update with Enable
    always @(posedge clk or negedge reset_n) begin
        if (!reset_n) begin
            f    <= 4'b0000;
            cout <= 1'b0;
        end else if (alu_en) begin
            f    <= next_f;
            cout <= next_cout;
        end
    end
endmodule

src/decoder_fsm.v
`timescale 1ns/1ps
`include "cpu_defs.vh"

module instruction_decoder (
    output reg        ram_csn, ram_rwn,
    output reg  [3:0] ram_addr, ram_data_in,
    output reg        alu_en,
    output reg  [3:0] alu_sel, alu_a, alu_b,
    input  wire       clk, reset_n,
    input  wire [10:0] instruction,
    input  wire [3:0] ram_data_out, alu_result
);

    wire [2:0] opcode = `GET_OPCODE(instruction);
    wire [3:0] op1    = `GET_OP1(instruction);
    wire [3:0] op2    = `GET_OP2(instruction);

    reg [1:0] current_state, next_state;

    always @(posedge clk or negedge reset_n)
        if (!reset_n) current_state <= `ST_INIT;
        else current_state <= next_state;

    always @(*) begin
        case (current_state)
            `ST_INIT:  next_state = `ST_FETCH;
            `ST_FETCH: next_state = `ST_EXEC;
            `ST_EXEC:  next_state = `ST_STORE;
            `ST_STORE: next_state = `ST_FETCH;
            default:   next_state = `ST_INIT;
        endcase
    end

    always @(*) begin
        // Defaults
        ram_csn = `RAM_IDLE; ram_rwn = `RAM_READ; ram_addr = 0; ram_data_in = 0;
        alu_en = 0; alu_sel = `ALU_TRANSFER; alu_a = 0; alu_b = 0;

        case (current_state)
            `ST_FETCH: begin
                ram_csn = `RAM_ACTIVE; ram_rwn = `RAM_READ; ram_addr = op1;
            end
            `ST_EXEC: begin
                ram_csn = `RAM_ACTIVE; ram_rwn = `RAM_READ; ram_addr = op1;
                alu_en = 1; // Enable ALU
                alu_b = op2;
                if (opcode == `OPC_STO) alu_a = 0; else alu_a = ram_data_out;
                
                case (opcode)
                    `OPC_STO: alu_sel = `ALU_ADD_AB;
                    `OPC_ADD: alu_sel = `ALU_ADD_AB;
                    `OPC_SUB: alu_sel = `ALU_SUB_A_B_1;
                    `OPC_AND: alu_sel = `ALU_AND_MASK;
                    `OPC_OR:  alu_sel = `ALU_OR_MASK;
                    `OPC_XOR: alu_sel = `ALU_XOR_MASK;
                    `OPC_NOT: alu_sel = `ALU_NOT_MASK;
                    default:  alu_sel = `ALU_TRANSFER;
                endcase
            end
            `ST_STORE: begin
                ram_csn = `RAM_ACTIVE; ram_rwn = `RAM_WRITE; ram_addr = op1; ram_data_in = alu_result;
                alu_en = 0; // Hold ALU
            end
        endcase
    end
endmodule

src/cpu_top.v
`timescale 1ns/1ps
`include "cpu_defs.vh"

module cpu_top (
    output wire [3:0]  debug_alu_res,
    output wire [3:0]  debug_ram_out,
    output wire        debug_cout,
    input  wire        clk,
    input  wire        reset_n,
    input  wire [10:0] instruction
);

    wire       ram_csn;
    wire       ram_rwn;
    wire [3:0] ram_addr;
    wire [3:0] ram_wdata;
    wire [3:0] ram_rdata;

    wire       alu_en;   // <--- Internal Wire
    wire [3:0] alu_sel;
    wire [3:0] alu_a;
    wire [3:0] alu_b;
    wire [3:0] alu_f;
    wire       alu_cout;

    instruction_decoder u_decoder (
        .ram_csn      (ram_csn),
        .ram_rwn      (ram_rwn),
        .ram_addr     (ram_addr),
        .ram_data_in  (ram_wdata),
        .alu_en       (alu_en),       // <--- Connected
        .alu_sel      (alu_sel),
        .alu_a        (alu_a),
        .alu_b        (alu_b),
        .clk          (clk),
        .reset_n      (reset_n),
        .instruction  (instruction),
        .ram_data_out (ram_rdata),
        .alu_result   (alu_f)
    );

    reg_alu u_alu (
        .f       (alu_f),
        .cout    (alu_cout),
        .clk     (clk),
        .reset_n (reset_n),
        .alu_en  (alu_en),            // <--- Connected
        .alu_sel (alu_sel),
        .a       (alu_a),
        .b       (alu_b)
    );

    ram16x4 u_ram (
        .data_out (ram_rdata),
        .data_in  (ram_wdata),
        .addr     (ram_addr),
        .csn      (ram_csn),
        .rwn      (ram_rwn),
        .clk      (clk),
        .rst_n    (reset_n)
    );

    assign debug_alu_res = alu_f;
    assign debug_ram_out = ram_rdata;
    assign debug_cout    = alu_cout;

endmodule

testbench/bridge_tb_step.v
`timescale 1ns/1ps
`include "cpu_defs.vh"

module cpu_tb_step;

    // Signals
    wire [3:0]  debug_alu_res;
    wire [3:0]  debug_ram_out;
    wire        debug_cout;
    reg         clk;
    reg         reset_n;
    reg  [10:0] instruction;

    // Instruction Memory (256 slots)
    reg [10:0] prog_mem [0:255];
    integer pc;
    integer sf, r; // file handles
    integer i;
    reg [3:0] acc_val;
    reg carry_val;
    reg [3:0] tmp_ram;
    reg [1023:0] ram_line;

    // For logging
    reg [23:0] op_str;

    // DUT
    cpu_top u_cpu (
        .debug_alu_res (debug_alu_res),
        .debug_ram_out (debug_ram_out),
        .debug_cout    (debug_cout),
        .clk           (clk),
        .reset_n       (reset_n),
        .instruction   (instruction)
    );

    // Clock
    initial begin
        clk = 0;
        forever #5 clk = ~clk;
    end

    // Waveform
    initial begin
        $dumpfile("simulation.vcd");
        $dumpvars(0, cpu_tb_step);
    end

    // MAIN: single-step execution using external state file
    initial begin

        // Load program
        $readmemh("program.hex", prog_mem);

        // Default state
        pc = 0;
        acc_val = 4'b0000;
        carry_val = 0;
        for (i = 0; i < 16; i = i + 1) u_cpu.u_ram.mem[i] = 4'b0000;

        // Reset pulse first (clear internals)
        reset_n = 0;
        @(posedge clk); @(posedge clk);
        reset_n = 1;
        @(negedge clk);

        // After reset, load the saved cpu_state (so reset doesn't overwrite it)
        sf = $fopen("cpu_state.hex", "r");
        if (sf) begin
            // Expected format:
            // PC <decimal>\n
            r = $fscanf(sf, "PC %d\n", pc);
            r = $fscanf(sf, "ACC %h\n", acc_val);
            r = $fscanf(sf, "CARRY %d\n", carry_val);

            // Read RAM line: 16 hex values
            for (i = 0; i < 16; i = i + 1) begin
                r = $fscanf(sf, "%h ", tmp_ram);
                u_cpu.u_ram.mem[i] = tmp_ram;
            end
            $fclose(sf);
        end

        // Restore accumulator and carry (reg_alu internals)
        u_cpu.u_alu.f = acc_val;
        u_cpu.u_alu.cout = carry_val;

        // Fetch instruction at PC
        instruction = prog_mem[pc];

        // If instruction undefined, nothing to do
        if (instruction === 11'bx) begin
            $display("[DONE]");
            $finish;
        end

        // Decode opcode string for logging
        case (`GET_OPCODE(instruction))
            `OPC_STO: op_str = "STO";
            `OPC_ADD: op_str = "ADD";
            `OPC_SUB: op_str = "SUB";
            `OPC_AND: op_str = "AND";
            `OPC_OR:  op_str = "OR ";
            `OPC_XOR: op_str = "XOR";
            `OPC_NOT: op_str = "NOT";
            default:  op_str = "???";
        endcase

        $display("[EXEC] PC:%0d | Op:%s | Dest:%h | Src:%h", pc, op_str, `GET_OP1(instruction), `GET_OP2(instruction));

        // Run one instruction cycle
        run_cycle();

        // After execution, capture updated RAM and ALU
        acc_val = u_cpu.u_alu.f;
        carry_val = u_cpu.u_alu.cout;

        // Increment PC (simple linear flow)
        pc = pc + 1;

        // Dump RAM values and write cpu_state.hex back
        // Also print RAM update for GUI (single dest read already printed by run_cycle)
        sf = $fopen("cpu_state.hex", "w");
        if (sf) begin
            $fdisplay(sf, "PC %0d", pc);
            $fdisplay(sf, "ACC %h", acc_val);
            $fdisplay(sf, "CARRY %0d", carry_val);
            // Write RAM as 16 hex values on one line
            for (i = 0; i < 16; i = i + 1) begin
                $fwrite(sf, "%h ", u_cpu.u_ram.mem[i]);
            end
            $fdisplay(sf, "");
            $fclose(sf);
        end

        $display("[DONE]");
        $finish;
    end

    // Run cycle task reused from bridge_tb
    task run_cycle;
        reg [3:0] dest;
        reg [3:0] ram_val;
        begin
            dest = `GET_OP1(instruction);
            // Wait 2 cycles to get to Store state
            repeat(2) @(posedge clk);
            #1;
            @(posedge clk);
            #1;

            // Peek at RAM to see the result
            ram_val = u_cpu.u_ram.mem[dest];
            $display("[RAM] Addr:%h Val:%h", dest, ram_val);
            @(negedge clk);
        end
    endtask

endmodule

tools/simulation.vcd
$date
	Tue Dec  9 15:03:04 2025
$end
$version
	Icarus Verilog
$end
$timescale
	1ps
$end
$scope module cpu_tb_step $end
$var wire 4 ! debug_ram_out [3:0] $end
$var wire 1 " debug_cout $end
$var wire 4 # debug_alu_res [3:0] $end
$var reg 4 $ acc_val [3:0] $end
$var reg 1 % carry_val $end
$var reg 1 & clk $end
$var reg 11 ' instruction [10:0] $end
$var reg 24 ( op_str [23:0] $end
$var reg 1 ) reset_n $end
$var reg 4 * tmp_ram [3:0] $end
$var integer 32 + i [31:0] $end
$var integer 32 , pc [31:0] $end
$var integer 32 - r [31:0] $end
$var integer 32 . sf [31:0] $end
$scope module u_cpu $end
$var wire 1 & clk $end
$var wire 4 / debug_alu_res [3:0] $end
$var wire 1 " debug_cout $end
$var wire 4 0 debug_ram_out [3:0] $end
$var wire 11 1 instruction [10:0] $end
$var wire 1 ) reset_n $end
$var wire 4 2 ram_wdata [3:0] $end
$var wire 1 3 ram_rwn $end
$var wire 4 4 ram_rdata [3:0] $end
$var wire 1 5 ram_csn $end
$var wire 4 6 ram_addr [3:0] $end
$var wire 4 7 alu_sel [3:0] $end
$var wire 4 8 alu_f [3:0] $end
$var wire 1 9 alu_en $end
$var wire 1 : alu_cout $end
$var wire 4 ; alu_b [3:0] $end
$var wire 4 < alu_a [3:0] $end
$scope module u_alu $end
$var wire 1 & clk $end
$var wire 1 ) reset_n $end
$var wire 4 = xor_res [3:0] $end
$var wire 4 > sum_out [3:0] $end
$var wire 1 ? s2 $end
$var wire 1 @ s1 $end
$var wire 1 A s0 $end
$var wire 4 B next_f [3:0] $end
$var wire 1 C next_cout $end
$var wire 1 D cout_arith $end
$var wire 1 E cin_in $end
$var wire 4 F b [3:0] $end
$var wire 4 G alu_sel [3:0] $end
$var wire 1 9 alu_en $end
$var wire 4 H a [3:0] $end
$var reg 4 I adder_b [3:0] $end
$var reg 1 : cout $end
$var reg 4 J f [3:0] $end
$var reg 4 K logic_res [3:0] $end
$scope module u_adder $end
$var wire 4 L b [3:0] $end
$var wire 1 E cin $end
$var wire 4 M sum [3:0] $end
$var wire 1 D cout $end
$var wire 1 N c3 $end
$var wire 1 O c2 $end
$var wire 1 P c1 $end
$var wire 4 Q a [3:0] $end
$scope module fa0 $end
$var wire 1 R a $end
$var wire 1 S b $end
$var wire 1 T c1 $end
$var wire 1 U c2 $end
$var wire 1 E cin $end
$var wire 1 P cout $end
$var wire 1 V sum $end
$var wire 1 W s_ab $end
$scope module u_xor_ab $end
$var wire 1 R a $end
$var wire 1 S b $end
$var wire 1 W c $end
$upscope $end
$scope module u_xor_sum $end
$var wire 1 W a $end
$var wire 1 E b $end
$var wire 1 V c $end
$upscope $end
$upscope $end
$scope module fa1 $end
$var wire 1 X a $end
$var wire 1 Y b $end
$var wire 1 Z c1 $end
$var wire 1 [ c2 $end
$var wire 1 P cin $end
$var wire 1 O cout $end
$var wire 1 \ sum $end
$var wire 1 ] s_ab $end
$scope module u_xor_ab $end
$var wire 1 X a $end
$var wire 1 Y b $end
$var wire 1 ] c $end
$upscope $end
$scope module u_xor_sum $end
$var wire 1 ] a $end
$var wire 1 P b $end
$var wire 1 \ c $end
$upscope $end
$upscope $end
$scope module fa2 $end
$var wire 1 ^ a $end
$var wire 1 _ b $end
$var wire 1 ` c1 $end
$var wire 1 a c2 $end
$var wire 1 O cin $end
$var wire 1 N cout $end
$var wire 1 b sum $end
$var wire 1 c s_ab $end
$scope module u_xor_ab $end
$var wire 1 ^ a $end
$var wire 1 _ b $end
$var wire 1 c c $end
$upscope $end
$scope module u_xor_sum $end
$var wire 1 c a $end
$var wire 1 O b $end
$var wire 1 b c $end
$upscope $end
$upscope $end
$scope module fa3 $end
$var wire 1 d a $end
$var wire 1 e b $end
$var wire 1 f c1 $end
$var wire 1 g c2 $end
$var wire 1 N cin $end
$var wire 1 D cout $end
$var wire 1 h sum $end
$var wire 1 i s_ab $end
$scope module u_xor_ab $end
$var wire 1 d a $end
$var wire 1 e b $end
$var wire 1 i c $end
$upscope $end
$scope module u_xor_sum $end
$var wire 1 i a $end
$var wire 1 N b $end
$var wire 1 h c $end
$upscope $end
$upscope $end
$upscope $end
$scope module u_xor0 $end
$var wire 1 j a $end
$var wire 1 k b $end
$var wire 1 l c $end
$upscope $end
$scope module u_xor1 $end
$var wire 1 m a $end
$var wire 1 n b $end
$var wire 1 o c $end
$upscope $end
$scope module u_xor2 $end
$var wire 1 p a $end
$var wire 1 q b $end
$var wire 1 r c $end
$upscope $end
$scope module u_xor3 $end
$var wire 1 s a $end
$var wire 1 t b $end
$var wire 1 u c $end
$upscope $end
$upscope $end
$scope module u_decoder $end
$var wire 4 v alu_result [3:0] $end
$var wire 1 & clk $end
$var wire 11 w instruction [10:0] $end
$var wire 1 ) reset_n $end
$var wire 4 x ram_data_out [3:0] $end
$var wire 3 y opcode [2:0] $end
$var wire 4 z op2 [3:0] $end
$var wire 4 { op1 [3:0] $end
$var reg 4 | alu_a [3:0] $end
$var reg 4 } alu_b [3:0] $end
$var reg 1 9 alu_en $end
$var reg 4 ~ alu_sel [3:0] $end
$var reg 2 !" current_state [1:0] $end
$var reg 2 "" next_state [1:0] $end
$var reg 4 #" ram_addr [3:0] $end
$var reg 1 5 ram_csn $end
$var reg 4 $" ram_data_in [3:0] $end
$var reg 1 3 ram_rwn $end
$upscope $end
$scope module u_ram $end
$var wire 4 %" addr [3:0] $end
$var wire 1 & clk $end
$var wire 1 5 csn $end
$var wire 4 &" data_in [3:0] $end
$var wire 1 ) rst_n $end
$var wire 1 3 rwn $end
$var reg 4 '" data_out [3:0] $end
$var integer 32 (" i [31:0] $end
$upscope $end
$upscope $end
$scope task run_cycle $end
$var reg 4 )" dest [3:0] $end
$var reg 4 *" ram_val [3:0] $end
$upscope $end
$upscope $end
$enddefinitions $end
$comment Show the parameter values. $end
$dumpall
$end
#0
$dumpvars
bx *"
bx )"
b10000 ("
b0 '"
b0 &"
b0 %"
b0 $"
b0 #"
b1 ""
b0 !"
b0 ~
b0 }
b0 |
bx {
bx z
bx y
b0 x
bx w
b0 v
0u
0t
0s
0r
0q
0p
0o
0n
0m
0l
0k
0j
0i
0h
0g
0f
0e
0d
0c
0b
0a
0`
0_
0^
0]
0\
0[
0Z
0Y
0X
0W
0V
0U
0T
0S
0R
b0 Q
0P
0O
0N
b0 M
b0 L
b0 K
b0 J
b0 I
b0 H
b0 G
b0 F
0E
0D
0C
b0 B
0A
0@
0?
b0 >
b0 =
b0 <
b0 ;
0:
09
b0 8
b0 7
b0 6
15
b0 4
13
b0 2
bx 1
b0 0
b0 /
bx .
bx -
b0 ,
b10000 +
bx *
0)
bx (
bx '
0&
0%
b0 $
b0 #
0"
b0 !
$end
#5000
b10000 ("
1&
#10000
0&
#15000
bx 6
bx #"
bx %"
05
b10 ""
b1 !"
1)
1&
#20000
b1 y
b111 {
b111 z
b111 6
b111 #"
b111 %"
05
b111 )"
b10000010100010001000100 (
b101110111 '
b101110111 1
b101110111 w
b10 #
b10 /
b10 8
b10 J
b10 v
b0 *
b10000 +
b10 $
b1 -
b1 ,
b10000000000000000000000000000011 .
0&
#25000
0\
1O
1h
1[
b1100 B
1P
1]
1N
1b
b1100 >
b1100 M
0V
1T
1`
1S
1Y
1_
0c
0W
0r
1o
b10 =
0l
b111 I
b111 L
1A
1^
1R
1p
1j
1q
1n
1k
b10 7
b10 G
b10 ~
b101 <
b101 H
b101 Q
b101 |
b111 ;
b111 F
b111 }
19
b111 6
b111 #"
b111 %"
05
b11 ""
b101 !
b101 0
b101 4
b101 x
b101 '"
b10 !"
1&
#30000
0&
#35000
0b
b0 B
b0 >
b0 M
0h
0O
0]
0[
b0 =
0o
0N
0P
0S
0Y
0_
0`
0T
0q
0n
0k
b0 I
b0 L
0^
0R
0p
0j
0A
b1 ""
b1100 2
b1100 $"
b1100 &"
03
b0 ;
b0 F
b0 }
b0 <
b0 H
b0 Q
b0 |
b0 7
b0 G
b0 ~
09
b111 6
b111 #"
b111 %"
05
b11 !"
b1100 #
b1100 /
b1100 8
b1100 J
b1100 v
1&
#40000
0&
#45000
b0 2
b0 $"
b0 &"
b111 6
b111 #"
b111 %"
13
05
b10 ""
b0 !
b0 0
b0 4
b0 x
b0 '"
b1 !"
1&
#46000
b1100 *"
#50000
b10000 +
b10 ,
b1100 $
0&
