src/cpu_defs.vh
`ifndef CPU_DEFS_VH
`define CPU_DEFS_VH

// ===========================================================
// CPU GLOBAL CONSTANTS / OPCODES / ALU CODES / STATES
// ===========================================================

// ---------- Instruction Format ----------
`define INSTR_W   11
`define ADDR_W    4
`define DATA_W    4

// Extract fields
`define GET_OPCODE(x)   (x[10:8])
`define GET_OP1(x)      (x[7:4])
`define GET_OP2(x)      (x[3:0])

// ---------- OPCODES ----------
`define OPC_STO   3'b000
`define OPC_ADD   3'b001
`define OPC_SUB   3'b010
`define OPC_AND   3'b011
`define OPC_OR    3'b100
`define OPC_XOR   3'b101
`define OPC_NOT   3'b110
// (3'b111 reserved)

// ---------- FSM States ----------
`define ST_INIT    2'b00
`define ST_FETCH   2'b01
`define ST_EXEC    2'b10
`define ST_STORE   2'b11

// ---------- ALU Select Codes ----------
// We'll use 4-bit ALU select tokens = {alu_sel[2:0], cin}
// Use `casez` in logic so '-'/'?' positions act as don't cares.

// Arithmetic / Transfer (cin is meaningful)
`define ALU_TRANSFER     4'b0000
`define ALU_INC          4'b0001

`define ALU_ADD_AB       4'b0010
`define ALU_ADD_ABCIN    4'b0011

`define ALU_SUB_A_B      4'b0100
`define ALU_SUB_A_B_1    4'b0101

`define ALU_DEC          4'b0110
`define ALU_PASS_A       4'b0111

// Logical Ops (cin ignored -> use '?' in pattern macros with casez)
`define ALU_OR_MASK      4'b100?   // casez pattern: matches 1000 or 1001
`define ALU_XOR_MASK     4'b101?   // matches 1010 or 1011
`define ALU_AND_MASK     4'b110?   // matches 1100 or 1101
`define ALU_NOT_MASK     4'b111?   // matches 1110 or 1111

// ---------- RAM Control ----------
`define RAM_ACTIVE  1'b0
`define RAM_IDLE    1'b1
`define RAM_READ    1'b1
`define RAM_WRITE   1'b0

`endif

src/ram16x4.v
`timescale 1ns/1ps

module ram16x4(
    output reg [3:0] data_out,
    input [3:0] data_in,
    input [3:0] addr,
    input csn,
    input rwn,
    input clk, rst_n
); 

reg [3:0] mem [15:0];

integer i;
always @(posedge clk or negedge rst_n) begin
    //Asynchronous Reset of RAM Memory
    if (!rst_n) begin
        for (i=0; i<16; i=i+1) begin
            mem[i] <= 4'b0000;
        end
    data_out <= 4'b0000;
    end

    else if (!csn) begin 
        if (!rwn) begin
            // WRITE operation
            mem[addr] <= data_in;
            data_out  <= 4'b0000;   
        end

        else begin
            // READ operation
            data_out <= mem[addr];
        end
    end

end

endmodule

src/xor_gate.v
`timescale 1ns/1ps

module xor_gate (
    input  wire a,
    input  wire b,
    output wire c
);
    assign c = (a & ~b) | (~a & b);
endmodule

src/full_adder1.v
`timescale 1ns/1ps

module full_adder1 (
    output wire sum,
    output wire cout,
    input  wire a,
    input  wire b,
    input  wire cin
);
    wire s_ab;      // a ^ b
    wire c1, c2;    // carry terms

    xor_gate u_xor_ab  (.c(s_ab), .a(a),    .b(b));
    xor_gate u_xor_sum (.c(sum),  .a(s_ab), .b(cin));

    assign c1  = a & b;
    assign c2  = cin & s_ab;
    assign cout = c1 | c2;
endmodule

src/full_adder4.v
`timescale 1ns/1ps

module full_adder4 (
    output wire [3:0] sum,
    output wire       cout,
    input  wire [3:0] a,
    input  wire [3:0] b,
    input  wire       cin
);
    // Internal carry wires
    wire c1, c2, c3;

    // Ripple Carry Architecture using full_adder1
    full_adder1 fa0 (.sum(sum[0]), .cout(c1),   .a(a[0]), .b(b[0]), .cin(cin));
    full_adder1 fa1 (.sum(sum[1]), .cout(c2),   .a(a[1]), .b(b[1]), .cin(c1));
    full_adder1 fa2 (.sum(sum[2]), .cout(c3),   .a(a[2]), .b(b[2]), .cin(c2));
    full_adder1 fa3 (.sum(sum[3]), .cout(cout), .a(a[3]), .b(b[3]), .cin(c3));

endmodule

src/reg_alu4.v
`timescale 1ns/1ps
`include "cpu_defs.vh"

module reg_alu (
    output reg  [3:0] f,
    output reg        cout,
    input  wire       clk,
    input  wire       reset_n,
    input  wire       alu_en,   // Clock Enable
    input  wire [3:0] alu_sel,
    input  wire [3:0] a,
    input  wire [3:0] b
);
    // 1. Decode & Arith Setup
    wire s2=alu_sel[3], s1=alu_sel[2], s0=alu_sel[1], cin_in=alu_sel[0];
    reg [3:0] adder_b;

    always @(*) begin
        case ({s1, s0})
            2'b00: adder_b = 4'b0000;
            2'b01: adder_b = b;
            2'b10: adder_b = ~b;
            2'b11: adder_b = 4'b1111;
        endcase
    end

    // 2. Calculation Units
    wire [3:0] sum_out;
    wire       cout_arith;
    full_adder4 u_adder (.sum(sum_out), .cout(cout_arith), .a(a), .b(adder_b), .cin(cin_in));

    reg [3:0] logic_res;
    wire [3:0] xor_res;
    xor_gate u_xor0 (.c(xor_res[0]), .a(a[0]), .b(b[0]));
    xor_gate u_xor1 (.c(xor_res[1]), .a(a[1]), .b(b[1]));
    xor_gate u_xor2 (.c(xor_res[2]), .a(a[2]), .b(b[2]));
    xor_gate u_xor3 (.c(xor_res[3]), .a(a[3]), .b(b[3]));

    always @(*) begin
        casez (alu_sel)
            `ALU_OR_MASK:  logic_res = a | b;
            `ALU_AND_MASK: logic_res = a & b;
            `ALU_XOR_MASK: logic_res = xor_res;
            `ALU_NOT_MASK: logic_res = ~a;
            default:       logic_res = 4'b0000;
        endcase
    end

    // 3. Output Logic
    wire [3:0] next_f    = (s2 == 1'b0) ? sum_out : logic_res;
    wire       next_cout = (s2 == 1'b0) ? cout_arith : 1'b0;

    // 4. Sequential Update with Enable
    always @(posedge clk or negedge reset_n) begin
        if (!reset_n) begin
            f    <= 4'b0000;
            cout <= 1'b0;
        end else if (alu_en) begin
            f    <= next_f;
            cout <= next_cout;
        end
    end
endmodule

src/decoder_fsm.v
`timescale 1ns/1ps
`include "cpu_defs.vh"

module instruction_decoder (
    output reg        ram_csn, ram_rwn,
    output reg  [3:0] ram_addr, ram_data_in,
    output reg        alu_en,
    output reg  [3:0] alu_sel, alu_a, alu_b,
    input  wire       clk, reset_n,
    input  wire [10:0] instruction,
    input  wire [3:0] ram_data_out, alu_result
);

    wire [2:0] opcode = `GET_OPCODE(instruction);
    wire [3:0] op1    = `GET_OP1(instruction);
    wire [3:0] op2    = `GET_OP2(instruction);

    reg [1:0] current_state, next_state;

    always @(posedge clk or negedge reset_n)
        if (!reset_n) current_state <= `ST_INIT;
        else current_state <= next_state;

    always @(*) begin
        case (current_state)
            `ST_INIT:  next_state = `ST_FETCH;
            `ST_FETCH: next_state = `ST_EXEC;
            `ST_EXEC:  next_state = `ST_STORE;
            `ST_STORE: next_state = `ST_FETCH;
            default:   next_state = `ST_INIT;
        endcase
    end

    always @(*) begin
        // Defaults
        ram_csn = `RAM_IDLE; ram_rwn = `RAM_READ; ram_addr = 0; ram_data_in = 0;
        alu_en = 0; alu_sel = `ALU_TRANSFER; alu_a = 0; alu_b = 0;

        case (current_state)
            `ST_FETCH: begin
                ram_csn = `RAM_ACTIVE; ram_rwn = `RAM_READ; ram_addr = op1;
            end
            `ST_EXEC: begin
                ram_csn = `RAM_ACTIVE; ram_rwn = `RAM_READ; ram_addr = op1;
                alu_en = 1; // Enable ALU
                alu_b = op2;
                if (opcode == `OPC_STO) alu_a = 0; else alu_a = ram_data_out;
                
                case (opcode)
                    `OPC_STO: alu_sel = `ALU_ADD_AB;
                    `OPC_ADD: alu_sel = `ALU_ADD_AB;
                    `OPC_SUB: alu_sel = `ALU_SUB_A_B_1;
                    `OPC_AND: alu_sel = `ALU_AND_MASK;
                    `OPC_OR:  alu_sel = `ALU_OR_MASK;
                    `OPC_XOR: alu_sel = `ALU_XOR_MASK;
                    `OPC_NOT: alu_sel = `ALU_NOT_MASK;
                    default:  alu_sel = `ALU_TRANSFER;
                endcase
            end
            `ST_STORE: begin
                ram_csn = `RAM_ACTIVE; ram_rwn = `RAM_WRITE; ram_addr = op1; ram_data_in = alu_result;
                alu_en = 0; // Hold ALU
            end
        endcase
    end
endmodule

src/cpu_top.v
`timescale 1ns/1ps
`include "cpu_defs.vh"

module cpu_top (
    output wire [3:0]  debug_alu_res,
    output wire [3:0]  debug_ram_out,
    output wire        debug_cout,
    input  wire        clk,
    input  wire        reset_n,
    input  wire [10:0] instruction
);

    wire       ram_csn;
    wire       ram_rwn;
    wire [3:0] ram_addr;
    wire [3:0] ram_wdata;
    wire [3:0] ram_rdata;

    wire       alu_en;   // <--- Internal Wire
    wire [3:0] alu_sel;
    wire [3:0] alu_a;
    wire [3:0] alu_b;
    wire [3:0] alu_f;
    wire       alu_cout;

    instruction_decoder u_decoder (
        .ram_csn      (ram_csn),
        .ram_rwn      (ram_rwn),
        .ram_addr     (ram_addr),
        .ram_data_in  (ram_wdata),
        .alu_en       (alu_en),       // <--- Connected
        .alu_sel      (alu_sel),
        .alu_a        (alu_a),
        .alu_b        (alu_b),
        .clk          (clk),
        .reset_n      (reset_n),
        .instruction  (instruction),
        .ram_data_out (ram_rdata),
        .alu_result   (alu_f)
    );

    reg_alu u_alu (
        .f       (alu_f),
        .cout    (alu_cout),
        .clk     (clk),
        .reset_n (reset_n),
        .alu_en  (alu_en),            // <--- Connected
        .alu_sel (alu_sel),
        .a       (alu_a),
        .b       (alu_b)
    );

    ram16x4 u_ram (
        .data_out (ram_rdata),
        .data_in  (ram_wdata),
        .addr     (ram_addr),
        .csn      (ram_csn),
        .rwn      (ram_rwn),
        .clk      (clk),
        .rst_n    (reset_n)
    );

    assign debug_alu_res = alu_f;
    assign debug_ram_out = ram_rdata;
    assign debug_cout    = alu_cout;

endmodule

testbench/bridge_tb.v
`timescale 1ns/1ps
`include "cpu_defs.vh"

module cpu_tb_gui;

    // ===============================================================
    // 1. SIGNALS
    // ===============================================================
    wire [3:0]  debug_alu_res;
    wire [3:0]  debug_ram_out;
    wire        debug_cout;
    
    reg         clk;
    reg         reset_n;
    reg  [10:0] instruction;

    // Instruction Memory (256 slots)
    reg [10:0] prog_mem [0:255]; 
    integer pc;

    // Helper for printing opcode strings
    reg [8*3:1] op_str; 

    // ===============================================================
    // 2. DUT INSTANTIATION
    // ===============================================================
    cpu_top u_cpu (
        .debug_alu_res (debug_alu_res),
        .debug_ram_out (debug_ram_out),
        .debug_cout    (debug_cout),
        .clk           (clk),
        .reset_n       (reset_n),
        .instruction   (instruction)
    );

    // ===============================================================
    // 3. CLOCK GENERATION
    // ===============================================================
    initial begin
        clk = 0;
        forever #5 clk = ~clk; 
    end

    // ===============================================================
    // WAVEFORM DUMPING (For GTKWave)
    // ===============================================================
    initial begin
        $dumpfile("simulation.vcd");
        $dumpvars(0, cpu_tb_gui);
    end
    
    // ===============================================================
    // 4. MAIN EXECUTION LOOP
    // ===============================================================
    initial begin
        // 1. Load the Hex File created by the GUI
        // The GUI MUST save "program.hex" before running this simulation
        $readmemh("program.hex", prog_mem);

        // 2. Initialize
        reset_n = 0;
        instruction = 0;

        // 3. Reset Sequence
        repeat(2) @(posedge clk);
        reset_n = 1;
        @(negedge clk); 

        // 4. Run Loop
        // We scan until we hit an undefined instruction (x) or limit
        for (pc = 0; pc < 256; pc = pc + 1) begin
            
            instruction = prog_mem[pc];

            // STOP Condition: Undefined instruction implies end of program
            if (instruction === 11'bx) begin
                $display("[DONE]"); // Signal to GUI that we finished
                $finish;
            end

            // Decode Opcode for logging
            case (`GET_OPCODE(instruction))
                `OPC_STO: op_str = "STO";
                `OPC_ADD: op_str = "ADD";
                `OPC_SUB: op_str = "SUB";
                `OPC_AND: op_str = "AND";
                `OPC_OR:  op_str = "OR ";
                `OPC_XOR: op_str = "XOR";
                `OPC_NOT: op_str = "NOT";
                default:  op_str = "???";
            endcase

            // Log the start of execution (Python reads this to highlight current line)
            $display("[EXEC] PC:%0d | Op:%s | Dest:%h | Src:%h", 
                     pc, op_str, `GET_OP1(instruction), `GET_OP2(instruction));

            // Run the hardware cycle
            run_cycle();
        end
        
        $display("[DONE]");
        $finish;
    end

    // ===============================================================
    // TASK: Run One Instruction & Log Updates
    // ===============================================================
    task run_cycle;
        reg [3:0] dest;
        reg [3:0] ram_val;
        
        // MOVED DECLARATIONS TO TOP (Fixes Syntax Error)
        integer file, r, inj_step, inj_addr, inj_val;

        begin
            dest = `GET_OP1(instruction);

            // 1. Execute (FETCH -> EXEC -> STORE)
            // Wait 2 cycles to get to Store state
            repeat(2) @(posedge clk);
            #1; 

            // (Optional: Log ALU intermediate result if needed)

            // Finish Write
            @(posedge clk);
            #1;

            // --- INJECTION LOGIC ---
            file = $fopen("injections.txt", "r");
            if (file) begin
                while (!$feof(file)) begin
                    r = $fscanf(file, "%d %h %h\n", inj_step, inj_addr, inj_val);
                    // If the injection is for the CURRENT step (pc counter), apply it
                    if (inj_step == pc) begin
                        // FORCE WRITE to RAM
                        u_cpu.u_ram.mem[inj_addr] = inj_val;
                        $display("[INJECT] Step:%0d RAM[%h]=%h", inj_step, inj_addr, inj_val);
                        // Also update our local view if we injected into the dest addr
                        if (inj_addr == dest) begin
                             // Wait small delay for write to settle? Not needed for blocking assignment
                        end
                    end
                end
                $fclose(file);
            end
            // -----------------------

            // 2. Peek at RAM to see the result
            ram_val = u_cpu.u_ram.mem[dest];

            // 3. Log the RAM Update (Python reads this to update the table)
            // Format: [RAM] Addr:<HexAddr> Val:<HexData>
            $display("[RAM] Addr:%h Val:%h", dest, ram_val);
            
            // Re-align
            @(negedge clk);
        end
    endtask

endmodule

tools/simulation.vcd
$date
	Thu Dec  4 22:47:46 2025
$end
$version
	Icarus Verilog
$end
$timescale
	1ps
$end
$scope module cpu_tb_gui $end
$var wire 4 ! debug_ram_out [3:0] $end
$var wire 1 " debug_cout $end
$var wire 4 # debug_alu_res [3:0] $end
$var reg 1 $ clk $end
$var reg 11 % instruction [10:0] $end
$var reg 24 & op_str [24:1] $end
$var reg 1 ' reset_n $end
$var integer 32 ( pc [31:0] $end
$scope module u_cpu $end
$var wire 1 $ clk $end
$var wire 4 ) debug_alu_res [3:0] $end
$var wire 1 " debug_cout $end
$var wire 4 * debug_ram_out [3:0] $end
$var wire 11 + instruction [10:0] $end
$var wire 1 ' reset_n $end
$var wire 4 , ram_wdata [3:0] $end
$var wire 1 - ram_rwn $end
$var wire 4 . ram_rdata [3:0] $end
$var wire 1 / ram_csn $end
$var wire 4 0 ram_addr [3:0] $end
$var wire 4 1 alu_sel [3:0] $end
$var wire 4 2 alu_f [3:0] $end
$var wire 1 3 alu_en $end
$var wire 1 4 alu_cout $end
$var wire 4 5 alu_b [3:0] $end
$var wire 4 6 alu_a [3:0] $end
$scope module u_alu $end
$var wire 1 $ clk $end
$var wire 1 ' reset_n $end
$var wire 4 7 xor_res [3:0] $end
$var wire 4 8 sum_out [3:0] $end
$var wire 1 9 s2 $end
$var wire 1 : s1 $end
$var wire 1 ; s0 $end
$var wire 4 < next_f [3:0] $end
$var wire 1 = next_cout $end
$var wire 1 > cout_arith $end
$var wire 1 ? cin_in $end
$var wire 4 @ b [3:0] $end
$var wire 4 A alu_sel [3:0] $end
$var wire 1 3 alu_en $end
$var wire 4 B a [3:0] $end
$var reg 4 C adder_b [3:0] $end
$var reg 1 4 cout $end
$var reg 4 D f [3:0] $end
$var reg 4 E logic_res [3:0] $end
$scope module u_adder $end
$var wire 4 F b [3:0] $end
$var wire 1 ? cin $end
$var wire 4 G sum [3:0] $end
$var wire 1 > cout $end
$var wire 1 H c3 $end
$var wire 1 I c2 $end
$var wire 1 J c1 $end
$var wire 4 K a [3:0] $end
$scope module fa0 $end
$var wire 1 L a $end
$var wire 1 M b $end
$var wire 1 N c1 $end
$var wire 1 O c2 $end
$var wire 1 ? cin $end
$var wire 1 J cout $end
$var wire 1 P sum $end
$var wire 1 Q s_ab $end
$scope module u_xor_ab $end
$var wire 1 L a $end
$var wire 1 M b $end
$var wire 1 Q c $end
$upscope $end
$scope module u_xor_sum $end
$var wire 1 Q a $end
$var wire 1 ? b $end
$var wire 1 P c $end
$upscope $end
$upscope $end
$scope module fa1 $end
$var wire 1 R a $end
$var wire 1 S b $end
$var wire 1 T c1 $end
$var wire 1 U c2 $end
$var wire 1 J cin $end
$var wire 1 I cout $end
$var wire 1 V sum $end
$var wire 1 W s_ab $end
$scope module u_xor_ab $end
$var wire 1 R a $end
$var wire 1 S b $end
$var wire 1 W c $end
$upscope $end
$scope module u_xor_sum $end
$var wire 1 W a $end
$var wire 1 J b $end
$var wire 1 V c $end
$upscope $end
$upscope $end
$scope module fa2 $end
$var wire 1 X a $end
$var wire 1 Y b $end
$var wire 1 Z c1 $end
$var wire 1 [ c2 $end
$var wire 1 I cin $end
$var wire 1 H cout $end
$var wire 1 \ sum $end
$var wire 1 ] s_ab $end
$scope module u_xor_ab $end
$var wire 1 X a $end
$var wire 1 Y b $end
$var wire 1 ] c $end
$upscope $end
$scope module u_xor_sum $end
$var wire 1 ] a $end
$var wire 1 I b $end
$var wire 1 \ c $end
$upscope $end
$upscope $end
$scope module fa3 $end
$var wire 1 ^ a $end
$var wire 1 _ b $end
$var wire 1 ` c1 $end
$var wire 1 a c2 $end
$var wire 1 H cin $end
$var wire 1 > cout $end
$var wire 1 b sum $end
$var wire 1 c s_ab $end
$scope module u_xor_ab $end
$var wire 1 ^ a $end
$var wire 1 _ b $end
$var wire 1 c c $end
$upscope $end
$scope module u_xor_sum $end
$var wire 1 c a $end
$var wire 1 H b $end
$var wire 1 b c $end
$upscope $end
$upscope $end
$upscope $end
$scope module u_xor0 $end
$var wire 1 d a $end
$var wire 1 e b $end
$var wire 1 f c $end
$upscope $end
$scope module u_xor1 $end
$var wire 1 g a $end
$var wire 1 h b $end
$var wire 1 i c $end
$upscope $end
$scope module u_xor2 $end
$var wire 1 j a $end
$var wire 1 k b $end
$var wire 1 l c $end
$upscope $end
$scope module u_xor3 $end
$var wire 1 m a $end
$var wire 1 n b $end
$var wire 1 o c $end
$upscope $end
$upscope $end
$scope module u_decoder $end
$var wire 4 p alu_result [3:0] $end
$var wire 1 $ clk $end
$var wire 11 q instruction [10:0] $end
$var wire 1 ' reset_n $end
$var wire 4 r ram_data_out [3:0] $end
$var wire 3 s opcode [2:0] $end
$var wire 4 t op2 [3:0] $end
$var wire 4 u op1 [3:0] $end
$var reg 4 v alu_a [3:0] $end
$var reg 4 w alu_b [3:0] $end
$var reg 1 3 alu_en $end
$var reg 4 x alu_sel [3:0] $end
$var reg 2 y current_state [1:0] $end
$var reg 2 z next_state [1:0] $end
$var reg 4 { ram_addr [3:0] $end
$var reg 1 / ram_csn $end
$var reg 4 | ram_data_in [3:0] $end
$var reg 1 - ram_rwn $end
$upscope $end
$scope module u_ram $end
$var wire 4 } addr [3:0] $end
$var wire 1 $ clk $end
$var wire 1 / csn $end
$var wire 4 ~ data_in [3:0] $end
$var wire 1 ' rst_n $end
$var wire 1 - rwn $end
$var reg 4 !" data_out [3:0] $end
$var integer 32 "" i [31:0] $end
$upscope $end
$upscope $end
$scope task run_cycle $end
$var reg 4 #" dest [3:0] $end
$var reg 4 $" ram_val [3:0] $end
$var integer 32 %" file [31:0] $end
$var integer 32 &" inj_addr [31:0] $end
$var integer 32 '" inj_step [31:0] $end
$var integer 32 (" inj_val [31:0] $end
$var integer 32 )" r [31:0] $end
$upscope $end
$upscope $end
$enddefinitions $end
$comment Show the parameter values. $end
$dumpall
$end
#0
$dumpvars
bx )"
bx ("
bx '"
bx &"
bx %"
bx $"
bx #"
b10000 ""
b0 !"
b0 ~
b0 }
b0 |
b0 {
b1 z
b0 y
b0 x
b0 w
b0 v
b0 u
b0 t
b0 s
b0 r
b0 q
b0 p
0o
0n
0m
0l
0k
0j
0i
0h
0g
0f
0e
0d
0c
0b
0a
0`
0_
0^
0]
0\
0[
0Z
0Y
0X
0W
0V
0U
0T
0S
0R
0Q
0P
0O
0N
0M
0L
b0 K
0J
0I
0H
b0 G
b0 F
b0 E
b0 D
b0 C
b0 B
b0 A
b0 @
0?
0>
0=
b0 <
0;
0:
09
b0 8
b0 7
b0 6
b0 5
04
03
b0 2
b0 1
b0 0
1/
b0 .
1-
b0 ,
b0 +
b0 *
b0 )
bx (
0'
bx &
b0 %
0$
b0 #
0"
b0 !
$end
#5000
b10000 ""
1$
#10000
0$
#15000
0/
b10 z
b1 y
1'
1$
#20000
b111 0
b111 {
b111 }
0/
b111 u
b10 t
b111 #"
b10100110101010001001111 &
b1110010 %
b1110010 +
b1110010 q
b0 (
0$
#25000
b10 <
b10 8
b10 G
1V
1W
1S
b10 7
1i
b10 C
b10 F
1;
1h
b10 1
b10 A
b10 x
b10 5
b10 @
b10 w
13
b111 0
b111 {
b111 }
0/
b11 z
b10 y
1$
#30000
0$
#35000
b0 <
b0 8
b0 G
0V
0W
b0 7
0i
0S
0h
b0 C
b0 F
0;
b1 z
b10 ,
b10 |
b10 ~
0-
b0 5
b0 @
b0 w
b0 1
b0 A
b0 x
03
b111 0
b111 {
b111 }
0/
b11 y
b10 #
b10 )
b10 2
b10 D
b10 p
1$
#40000
0$
#45000
b0 ,
b0 |
b0 ~
b111 0
b111 {
b111 }
1-
0/
b10 z
b1 y
1$
#46000
b10 $"
b0 %"
#50000
b111 0
b111 {
b111 }
0/
b1 s
b111 t
b10000010100010001000100 &
b101110111 %
b101110111 +
b101110111 q
b1 (
0$
#55000
1b
1P
0\
1H
1[
b1001 <
1Q
1I
1]
b1001 8
b1001 G
0V
1T
1M
1S
1Y
0W
1l
0i
b101 7
1f
b111 C
b111 F
1;
1R
1g
1k
1h
1e
b11 z
b10 1
b10 A
b10 x
b10 6
b10 B
b10 K
b10 v
b111 5
b111 @
b111 w
13
b111 0
b111 {
b111 }
0/
b10 y
b10 !
b10 *
b10 .
b10 r
b10 !"
1$
#60000
0$
#65000
b0 <
0b
b0 8
b0 G
0P
0H
0Q
0]
0[
0l
b0 7
0f
0I
0M
0S
0Y
0T
0k
0h
0e
b0 C
b0 F
0R
0g
0;
b1001 ,
b1001 |
b1001 ~
0-
b0 5
b0 @
b0 w
b0 6
b0 B
b0 K
b0 v
b0 1
b0 A
b0 x
03
b111 0
b111 {
b111 }
0/
b1 z
b1001 #
b1001 )
b1001 2
b1001 D
b1001 p
b11 y
1$
#70000
0$
#75000
b10 z
b0 ,
b0 |
b0 ~
b111 0
b111 {
b111 }
1-
0/
b1 y
b0 !
b0 *
b0 .
b0 r
b0 !"
1$
#76000
b1001 $"
#80000
b10 0
b10 {
b10 }
0/
b0 s
b10 u
b1001 t
b10 #"
b10100110101010001001111 &
b101001 %
b101001 +
b101001 q
b10 (
0$
#85000
b1001 <
1P
b1001 8
b1001 G
1b
1Q
1c
1M
1_
1o
b1001 7
1f
b1001 C
b1001 F
1;
1n
1e
b10 1
b10 A
b10 x
b1001 5
b1001 @
b1001 w
13
b10 0
b10 {
b10 }
0/
b11 z
b10 y
1$
#90000
0$
#95000
b0 <
0P
b0 8
b0 G
0b
0Q
0c
0o
b0 7
0f
0M
0_
0n
0e
b0 C
b0 F
0;
b1001 ,
b1001 |
b1001 ~
0-
b0 5
b0 @
b0 w
b0 1
b0 A
b0 x
03
b10 0
b10 {
b10 }
0/
b1 z
b11 y
1$
#100000
0$
#105000
b0 ,
b0 |
b0 ~
b10 0
b10 {
b10 }
1-
0/
b10 z
b1 y
1$
#110000
b10 0
b10 {
b10 }
0/
b10 s
b100 t
b10100110101010101000010 &
b1000100100 %
b1000100100 +
b1000100100 q
b11 (
0$
#115000
1\
1I
0V
1=
1U
1W
1>
0b
1J
b101 <
1N
1`
0O
b101 8
b101 G
1P
1M
1S
1_
0c
0Q
1o
1f
b1101 7
1l
b1011 C
b1011 F
1?
1:
1^
1L
1m
1d
1k
b11 z
b101 1
b101 A
b101 x
b1001 6
b1001 B
b1001 K
b1001 v
b100 5
b100 @
b100 w
13
b10 0
b10 {
b10 }
0/
b10 y
b1001 !
b1001 *
b1001 .
b1001 r
b1001 !"
1$
#120000
0$
#125000
0\
0I
0W
0=
0U
b0 <
0l
0>
0J
0o
b0 7
0f
b0 8
b0 G
0P
0M
0S
0_
0`
0N
0k
b0 C
b0 F
0^
0L
0m
0d
0?
0:
b101 ,
b101 |
b101 ~
0-
b0 5
b0 @
b0 w
b0 6
b0 B
b0 K
b0 v
b0 1
b0 A
b0 x
03
b10 0
b10 {
b10 }
0/
b1 z
1"
14
b101 #
b101 )
b101 2
b101 D
b101 p
b11 y
1$
#130000
0$
#135000
b10 z
b0 ,
b0 |
b0 ~
b10 0
b10 {
b10 }
1-
0/
b1 y
b0 !
b0 *
b0 .
b0 r
b0 !"
1$
#136000
b101 $"
#140000
b1111 0
b1111 {
b1111 }
0/
b0 s
b1111 u
b1010 t
b1111 #"
b10100110101010001001111 &
b11111010 %
b11111010 +
b11111010 q
b100 (
0$
#145000
b1010 <
1V
b1010 8
b1010 G
1b
1W
1c
1S
1_
1o
b1010 7
1i
b1010 C
b1010 F
1;
1n
1h
b10 1
b10 A
b10 x
b1010 5
b1010 @
b1010 w
13
b1111 0
b1111 {
b1111 }
0/
b11 z
b10 y
1$
#150000
0$
#155000
b0 <
0V
b0 8
b0 G
0b
0W
0c
0o
b0 7
0i
0S
0_
0n
0h
b0 C
b0 F
0;
b1 z
b1010 ,
b1010 |
b1010 ~
0-
b0 5
b0 @
b0 w
b0 1
b0 A
b0 x
03
b1111 0
b1111 {
b1111 }
0/
b11 y
0"
04
b1010 #
b1010 )
b1010 2
b1010 D
b1010 p
1$
#160000
0$
#165000
b0 ,
b0 |
b0 ~
b1111 0
b1111 {
b1111 }
1-
0/
b10 z
b1 y
1$
#166000
b1010 $"
#170000
b1111 0
b1111 {
b1111 }
0/
b110 s
b0 t
b10011100100111101010100 &
b11011110000 %
b11011110000 +
b11011110000 q
b101 (
0$
#175000
xJ
0\
1H
xO
1[
1Q
1I
1]
1>
1b
xV
1T
1`
b10xx 8
b10xx G
xP
1M
1S
1Y
1_
b101 <
0c
0W
1o
b1010 7
1i
b1111 C
b1111 F
z?
1;
1:
19
1^
1R
1m
1g
b101 E
b11 z
b111z 1
b111z A
b111z x
b1010 6
b1010 B
b1010 K
b1010 v
13
b1111 0
b1111 {
b1111 }
0/
b10 y
b1010 !
b1010 *
b1010 .
b1010 r
b1010 !"
1$
#180000
0$
#185000
0b
0H
0V
0Q
0]
0[
b0 8
b0 G
0P
0>
0I
0o
b0 7
0i
0J
0M
0S
0Y
0_
0=
0`
0T
0O
b0 C
b0 F
b0 <
0^
0R
0m
0g
0?
0;
0:
09
b0 E
b101 ,
b101 |
b101 ~
0-
b0 6
b0 B
b0 K
b0 v
b0 1
b0 A
b0 x
03
b1111 0
b1111 {
b1111 }
0/
b1 z
b101 #
b101 )
b101 2
b101 D
b101 p
b11 y
1$
#190000
0$
#195000
b10 z
b0 ,
b0 |
b0 ~
b1111 0
b1111 {
b1111 }
1-
0/
b1 y
b0 !
b0 *
b0 .
b0 r
b0 !"
1$
#196000
b101 $"
#200000
bx 0
bx {
bx }
0/
bx s
bx u
bx t
bx %
bx +
bx q
b110 (
0$
